FeatureInsight/EDA_Investigation.py
FeatureInsight/__init__.py
FeatureInsight/structure_Investigation.py
FeatureInsight/untitled.py
FeatureInsight/shell/__init__.py
FeatureInsight/shell/usage.py
FeatureInsight-0.0.9.dist-info/LICENSE
FeatureInsight-0.0.9.dist-info/METADATA
FeatureInsight-0.0.9.dist-info/WHEEL
FeatureInsight-0.0.9.dist-info/entry_points.txt
FeatureInsight-0.0.9.dist-info/top_level.txt
FeatureInsight-0.0.9.dist-info/zip-safe
FeatureInsight-0.0.9.dist-info/RECORD
